{
	"items": [
		{
			"_id": "5c6687d65e9d882c8841f0fd",
			"_tpl": "55d7217a4bdc2d86028b456d"
		},
		{
			"_id": "5c6687d65e9d882c8841f121",
			"_tpl": "557ffd194bdc2d28148b457f",
			"parentId": "5c6687d65e9d882c8841f0fd",
			"slotId": "Pockets"
		},
		{
			"_id": "5c6687d65e9d882c8841f0fc",
			"_tpl": "566abbc34bdc2d92178b4576"
		},
		{
			"_id": "5c6687d65e9d882c8841f0ff",
			"_tpl": "5963866b86f7747bfa1c4462"
		},
		{
			"_id": "5c6687d65e9d882c8841f0fe",
			"_tpl": "5963866286f7747bf429b572"
		},
		{
			"_id": "B51642353926194063lznaLk",
			"_tpl": "5ca20abf86f77418567a43f2",
			"parentId": "5c6687d65e9d882c8841f0fd",
			"slotId": "TacticalVest"
		},
		{
			"_id": "I210136106578779276VV4Bj",
			"_tpl": "574d967124597745970e7c94",
			"parentId": "5c6687d65e9d882c8841f0fd",
			"slotId": "FirstPrimaryWeapon"
		},
		{
			"_id": "I210136107423767355tZpdj",
			"_tpl": "587e0531245977466077a0f7",
			"parentId": "I210136106578779276VV4Bj",
			"slotId": "mod_stock"
		},
		{
			"_id": "I210136105874836980imYaH",
			"_tpl": "574db213245977459a2f3f5d",
			"parentId": "I210136106578779276VV4Bj",
			"slotId": "mod_sight_rear",
			"upd": {
				"Sight": {
					"SelectedSightMode": 0
				}
			}
		},
		{
			"_id": "MagazineWeaponScav9737",
			"_tpl": "5c5970672e221602b21d7855",
			"parentId": "I210136106578779276VV4Bj",
			"slotId": "mod_magazine"
		},
		{
			"_id": "AmmoMag16267",
			"_tpl": "59e4d24686f7741776641ac7",
			"parentId": "MagazineWeaponScav9737",
			"slotId": "cartridges",
			"upd": {
				"StackObjectsCount": 35
			}
		},
		{
			"_id": "I210136109303431157LuAtA",
			"_tpl": "593d490386f7745ee97a1555",
			"parentId": "I210136106578779276VV4Bj",
			"slotId": "mod_muzzle"
		},
		{
			"_id": "FuckYouUnlimitedAmmo965512",
			"_tpl": "5857a8bc2459772bad15db29",
			"parentId": "5c6687d65e9d882c8841f0fd",
			"slotId": "SecuredContainer"
		},
		{
			"_id": "iHateThatShit152004",
			"_tpl": "59e4d24686f7741776641ac7",
			"parentId": "FuckYouUnlimitedAmmo965512",
			"slotId": "main",
			"upd": {
				"StackObjectsCount": 60
			}
		},
		{
			"_id": "iHateThatShit169299",
			"_tpl": "59e4d3d286f774176a36250a",
			"parentId": "FuckYouUnlimitedAmmo965512",
			"slotId": "main",
			"upd": {
				"StackObjectsCount": 60
			}
		},
		{
			"_id": "iHateThatShit738720",
			"_tpl": "59e4d24686f7741776641ac7",
			"parentId": "FuckYouUnlimitedAmmo965512",
			"slotId": "main",
			"upd": {
				"StackObjectsCount": 60
			}
		},
		{
			"_id": "iHateThatShit308373",
			"_tpl": "59e4d3d286f774176a36250a",
			"parentId": "FuckYouUnlimitedAmmo965512",
			"slotId": "main",
			"upd": {
				"StackObjectsCount": 60
			}
		},
		{
			"_id": "iHateThatShit581969",
			"_tpl": "59e4cf5286f7741778269d8a",
			"parentId": "FuckYouUnlimitedAmmo965512",
			"slotId": "main",
			"upd": {
				"StackObjectsCount": 60
			}
		},
		{
			"_id": "iHateThatShit375673",
			"_tpl": "5656d7c34bdc2d9d198b4587",
			"parentId": "FuckYouUnlimitedAmmo965512",
			"slotId": "main",
			"upd": {
				"StackObjectsCount": 60
			}
		},
		{
			"_id": "iHateThatShit883157",
			"_tpl": "5656d7c34bdc2d9d198b4587",
			"parentId": "FuckYouUnlimitedAmmo965512",
			"slotId": "main",
			"upd": {
				"StackObjectsCount": 60
			}
		},
		{
			"_id": "iHateThatShit894037",
			"_tpl": "59e4d24686f7741776641ac7",
			"parentId": "FuckYouUnlimitedAmmo965512",
			"slotId": "main",
			"upd": {
				"StackObjectsCount": 60
			}
		},
		{
			"_id": "iHateThatShit601952",
			"_tpl": "59e4cf5286f7741778269d8a",
			"parentId": "FuckYouUnlimitedAmmo965512",
			"slotId": "main",
			"upd": {
				"StackObjectsCount": 60
			}
		},
		{
			"_id": "mag0Vest92910",
			"_tpl": "5c5970672e221602b21d7855",
			"parentId": "B51642353926194063lznaLk",
			"slotId": "1",
			"location": {
				"x": 0,
				"y": 0,
				"r": "Horizontal"
			}
		},
		{
			"_id": "AmmoMag0Vest133875",
			"_tpl": "59e4cf5286f7741778269d8a",
			"parentId": "mag0Vest92910",
			"slotId": "cartridges",
			"upd": {
				"StackObjectsCount": 35
			}
		},
		{
			"_id": "mag1Vest916151",
			"_tpl": "5c5970672e221602b21d7855",
			"parentId": "B51642353926194063lznaLk",
			"slotId": "3",
			"location": {
				"x": 0,
				"y": 0,
				"r": "Horizontal"
			}
		},
		{
			"_id": "AmmoMag1Vest451662",
			"_tpl": "59e4d3d286f774176a36250a",
			"parentId": "mag1Vest916151",
			"slotId": "cartridges",
			"upd": {
				"StackObjectsCount": 35
			}
		},
		{
			"_id": "mag3Vest997276",
			"_tpl": "5c5970672e221602b21d7855",
			"parentId": "B51642353926194063lznaLk",
			"slotId": "6",
			"location": {
				"x": 0,
				"y": 0,
				"r": "Horizontal"
			}
		},
		{
			"_id": "AmmoMag3Vest705177",
			"_tpl": "5656d7c34bdc2d9d198b4587",
			"parentId": "mag3Vest997276",
			"slotId": "cartridges",
			"upd": {
				"StackObjectsCount": 35
			}
		},
		{
			"_id": "mag4Vest624741",
			"_tpl": "5c5970672e221602b21d7855",
			"parentId": "B51642353926194063lznaLk",
			"slotId": "8",
			"location": {
				"x": 0,
				"y": 0,
				"r": "Horizontal"
			}
		},
		{
			"_id": "AmmoMag4Vest535889",
			"_tpl": "59e4cf5286f7741778269d8a",
			"parentId": "mag4Vest624741",
			"slotId": "cartridges",
			"upd": {
				"StackObjectsCount": 35
			}
		},
		{
			"_id": "B51642358995974304TKSz4l",
			"_tpl": "57e26ea924597715ca604a09",
			"parentId": "5c6687d65e9d882c8841f0fd",
			"slotId": "Scabbard"
		},
		{
			"_id": "B51642357796695777UlVu4q",
			"_tpl": "5b40e3f35acfc40016388218",
			"parentId": "5c6687d65e9d882c8841f0fd",
			"slotId": "Headwear"
		},
		{
			"_id": "B51642358540929006qmFqUW",
			"_tpl": "5aa2b986e5b5b00014028f4c",
			"parentId": "5c6687d65e9d882c8841f0fd",
			"slotId": "Eyewear"
		},
		{
			"_id": "B51642359215814626wIOeY5",
			"_tpl": "5b4325355acfc40019478126",
			"parentId": "5c6687d65e9d882c8841f0fd",
			"slotId": "FaceCover"
		},
		{
			"_id": "B51642358591513031kFCwl8",
			"_tpl": "56e335e4d2720b6c058b456d",
			"parentId": "5c6687d65e9d882c8841f0fd",
			"slotId": "Backpack"
		},
		{
			"_id": "BP51642351929682437LZpNO",
			"_tpl": "571a282c2459771fb2755a69",
			"parentId": "B51642358591513031kFCwl8",
			"slotId": "main",
			"location": {
				"x": 0,
				"y": 0,
				"r": "Horizontal"
			}
		},
		{
			"_id": "BP51642356012019850SFco4",
			"_tpl": "57514643245977207f2c2d09",
			"parentId": "B51642358591513031kFCwl8",
			"slotId": "main",
			"location": {
				"x": 0,
				"y": 1,
				"r": "Horizontal"
			}
		},
		{
			"_id": "BP51642358509078609COvlo",
			"_tpl": "55d4837c4bdc2d1d4e8b456c",
			"parentId": "B51642358591513031kFCwl8",
			"slotId": "main",
			"location": {
				"x": 0,
				"y": 2,
				"r": "Horizontal"
			}
		},
		{
			"_id": "B516423571932707052LXIyv",
			"_tpl": "5c0e5edb86f77461f55ed1f7",
			"parentId": "5c6687d65e9d882c8841f0fd",
			"slotId": "ArmorVest",
			"upd": {
				"Repairable": {
					"MaxDurability": 50,
					"Durability": 24
				}
			}
		},
		{
			"_id": "Pocket_114295",
			"_tpl": "59e366c186f7741778269d85",
			"parentId": "5c6687d65e9d882c8841f121",
			"slotId": "pocket1",
			"location": {
				"x": 0,
				"y": 0,
				"r": "Horizontal"
			},
			"upd": {
				"SpawnedInSession": true
			}
		},
		{
			"_id": "Pocket_73916",
			"_tpl": "5a718b548dc32e000d46d262",
			"parentId": "5c6687d65e9d882c8841f121",
			"slotId": "pocket2",
			"location": {
				"x": 0,
				"y": 0,
				"r": "Horizontal"
			},
			"upd": {
				"SpawnedInSession": true
			}
		}
	],
	"equipment": "5c6687d65e9d882c8841f0fd",
	"stash": "5c6687d65e9d882c8841f0fc",
	"questRaidItems": "5c6687d65e9d882c8841f0fe",
	"questStashItems": "5c6687d65e9d882c8841f0ff",
	"fastPanel": {}
}