{
	"items": [
		{
			"_id": "5c6687d65e9d882c8841f0fd",
			"_tpl": "55d7217a4bdc2d86028b456d"
		},
		{
			"_id": "5c6687d65e9d882c8841f121",
			"_tpl": "557ffd194bdc2d28148b457f",
			"parentId": "5c6687d65e9d882c8841f0fd",
			"slotId": "Pockets"
		},
		{
			"_id": "5c6687d65e9d882c8841f0fc",
			"_tpl": "566abbc34bdc2d92178b4576"
		},
		{
			"_id": "5c6687d65e9d882c8841f0ff",
			"_tpl": "5963866b86f7747bfa1c4462"
		},
		{
			"_id": "5c6687d65e9d882c8841f0fe",
			"_tpl": "5963866286f7747bf429b572"
		},
		{
			"_id": "B51642398278805178vaIyRc",
			"_tpl": "5ab8dced86f774646209ec87",
			"parentId": "5c6687d65e9d882c8841f0fd",
			"slotId": "TacticalVest"
		},
		{
			"_id": "I21017337921233979WEO4vF",
			"_tpl": "55801eed4bdc2d89578b4588",
			"parentId": "5c6687d65e9d882c8841f0fd",
			"slotId": "FirstPrimaryWeapon"
		},
		{
			"_id": "MagazineWeaponScav5456",
			"_tpl": "559ba5b34bdc2d1f1a8b4582",
			"parentId": "I21017337921233979WEO4vF",
			"slotId": "mod_magazine"
		},
		{
			"_id": "AmmoMag12881",
			"_tpl": "5e023d48186a883be655e551",
			"parentId": "MagazineWeaponScav5456",
			"slotId": "cartridges",
			"upd": {
				"StackObjectsCount": 10
			}
		},
		{
			"_id": "I21017336463144154PA6cjn",
			"_tpl": "5b2389515acfc4771e1be0c0",
			"parentId": "I21017337921233979WEO4vF",
			"slotId": "mod_scope"
		},
		{
			"_id": "I21017336709916131mTJDi2",
			"_tpl": "56083eab4bdc2d26448b456a",
			"parentId": "I21017337921233979WEO4vF",
			"slotId": "mod_tactical"
		},
		{
			"_id": "I21017337598911071iEQTAW",
			"_tpl": "5c4eec9b2e2216398b5aaba2",
			"parentId": "I21017337921233979WEO4vF",
			"slotId": "mod_muzzle"
		},
		{
			"_id": "I210173340901022313fL9uR",
			"_tpl": "56ea8222d2720b69698b4567",
			"parentId": "I21017337921233979WEO4vF",
			"slotId": "mod_bipod"
		},
		{
			"_id": "I21017332834614659Eum5uZ",
			"_tpl": "5887431f2459777e1612938f",
			"parentId": "I21017337608731717jYgq1L",
			"slotId": "cartridges",
			"location": 0,
			"upd": {
				"StackObjectsCount": 10
			}
		},
		{
			"_id": "I21017336867664274f4sOdb",
			"_tpl": "5a37cb10c4a282329a73b4e7",
			"parentId": "I21017336463144154PA6cjn",
			"slotId": "mod_scope_000",
			"upd": {
				"Sight": {
					"SelectedSightMode": 0
				}
			}
		},
		{
			"_id": "I210173342380403355b9n5J",
			"_tpl": "5c4eecc32e221602b412b440",
			"parentId": "I21017337598911071iEQTAW",
			"slotId": "mod_muzzle"
		},
		{
			"_id": "FuckYouUnlimitedAmmo5823",
			"_tpl": "5857a8bc2459772bad15db29",
			"parentId": "5c6687d65e9d882c8841f0fd",
			"slotId": "SecuredContainer"
		},
		{
			"_id": "iHateThatShit982231",
			"_tpl": "5887431f2459777e1612938f",
			"parentId": "FuckYouUnlimitedAmmo5823",
			"slotId": "main",
			"upd": {
				"StackObjectsCount": 60
			}
		},
		{
			"_id": "iHateThatShit141004",
			"_tpl": "5e023cf8186a883be655e54f",
			"parentId": "FuckYouUnlimitedAmmo5823",
			"slotId": "main",
			"upd": {
				"StackObjectsCount": 60
			}
		},
		{
			"_id": "iHateThatShit44129",
			"_tpl": "5887431f2459777e1612938f",
			"parentId": "FuckYouUnlimitedAmmo5823",
			"slotId": "main",
			"upd": {
				"StackObjectsCount": 60
			}
		},
		{
			"_id": "iHateThatShit781457",
			"_tpl": "560d61e84bdc2da74d8b4571",
			"parentId": "FuckYouUnlimitedAmmo5823",
			"slotId": "main",
			"upd": {
				"StackObjectsCount": 60
			}
		},
		{
			"_id": "iHateThatShit658883",
			"_tpl": "5e023d48186a883be655e551",
			"parentId": "FuckYouUnlimitedAmmo5823",
			"slotId": "main",
			"upd": {
				"StackObjectsCount": 60
			}
		},
		{
			"_id": "iHateThatShit141986",
			"_tpl": "5e023d34e8a400319a28ed44",
			"parentId": "FuckYouUnlimitedAmmo5823",
			"slotId": "main",
			"upd": {
				"StackObjectsCount": 60
			}
		},
		{
			"_id": "iHateThatShit968806",
			"_tpl": "59e77a2386f7742ee578960a",
			"parentId": "FuckYouUnlimitedAmmo5823",
			"slotId": "main",
			"upd": {
				"StackObjectsCount": 60
			}
		},
		{
			"_id": "iHateThatShit762329",
			"_tpl": "5e023cf8186a883be655e54f",
			"parentId": "FuckYouUnlimitedAmmo5823",
			"slotId": "main",
			"upd": {
				"StackObjectsCount": 60
			}
		},
		{
			"_id": "iHateThatShit208669",
			"_tpl": "5e023cf8186a883be655e54f",
			"parentId": "FuckYouUnlimitedAmmo5823",
			"slotId": "main",
			"upd": {
				"StackObjectsCount": 60
			}
		},
		{
			"_id": "I08203557431713583exnvxD",
			"_tpl": "5a7ae0c351dfba0017554310",
			"parentId": "5c6687d65e9d882c8841f0fd",
			"slotId": "Holster"
		},
		{
			"_id": "I08203555426613394ntIW2I",
			"_tpl": "5a6b5e468dc32e001207faf5",
			"parentId": "I08203557431713583exnvxD",
			"slotId": "mod_barrel",
			"upd": {
				"SpawnedInSession": true
			}
		},
		{
			"_id": "I08203558097747537lxztiB",
			"_tpl": "5a7b4960e899ef197b331a2d",
			"parentId": "I08203557431713583exnvxD",
			"slotId": "mod_pistol_grip",
			"upd": {
				"SpawnedInSession": true
			}
		},
		{
			"_id": "I08203558573784030vwv8I3",
			"_tpl": "5a71e22f8dc32e00094b97f4",
			"parentId": "I08203557431713583exnvxD",
			"slotId": "mod_reciever",
			"upd": {
				"SpawnedInSession": true
			}
		},
		{
			"_id": "AmmoMag144182",
			"_tpl": "5a3c16fe86f77452b62de32a",
			"parentId": "I08203552780873012Nn4gLm",
			"slotId": "cartridges",
			"upd": {
				"StackObjectsCount": 50
			}
		},
		{
			"_id": "I08203552780873012Nn4gLm",
			"_tpl": "5a718f958dc32e00094b97e7",
			"parentId": "I08203557431713583exnvxD",
			"slotId": "mod_magazine",
			"upd": {
				"SpawnedInSession": true
			}
		},
		{
			"_id": "I08203552555200049PQuHBz",
			"_tpl": "5cc9c20cd7f00c001336c65d",
			"parentId": "I08203557431713583exnvxD",
			"slotId": "mod_tactical",
			"upd": {
				"SpawnedInSession": true
			}
		},
		{
			"_id": "I08203553259039679gBUVUM",
			"_tpl": "5a7ad55551dfba0015068f42",
			"parentId": "I08203557431713583exnvxD",
			"slotId": "mod_mount",
			"upd": {
				"SpawnedInSession": true
			}
		},
		{
			"_id": "I08203552066094908ZNdxeZ",
			"_tpl": "5c6165902e22160010261b28",
			"parentId": "I08203555426613394ntIW2I",
			"slotId": "mod_muzzle",
			"upd": {
				"SpawnedInSession": true
			}
		},
		{
			"_id": "I08203552597583877TTEUx7",
			"_tpl": "57ae0171245977343c27bfcf",
			"parentId": "I08203553259039679gBUVUM",
			"slotId": "mod_scope",
			"upd": {
				"SpawnedInSession": true
			}
		},
		{
			"_id": "mag0Vest813720",
			"_tpl": "559ba5b34bdc2d1f1a8b4582",
			"parentId": "B51642398278805178vaIyRc",
			"slotId": "1",
			"location": {
				"x": 0,
				"y": 0,
				"r": "Horizontal"
			}
		},
		{
			"_id": "AmmoMag0Vest233244",
			"_tpl": "5e023d48186a883be655e551",
			"parentId": "mag0Vest813720",
			"slotId": "cartridges",
			"upd": {
				"StackObjectsCount": 10
			}
		},
		{
			"_id": "mag0Vest540378",
			"_tpl": "559ba5b34bdc2d1f1a8b4582",
			"parentId": "B51642398278805178vaIyRc",
			"slotId": "1",
			"location": {
				"x": 0,
				"y": 1,
				"r": "Horizontal"
			}
		},
		{
			"_id": "AmmoMag0Vest832581",
			"_tpl": "59e77a2386f7742ee578960a",
			"parentId": "mag0Vest540378",
			"slotId": "cartridges",
			"upd": {
				"StackObjectsCount": 10
			}
		},
		{
			"_id": "mag2Vest483488",
			"_tpl": "559ba5b34bdc2d1f1a8b4582",
			"parentId": "B51642398278805178vaIyRc",
			"slotId": "4",
			"location": {
				"x": 0,
				"y": 0,
				"r": "Horizontal"
			}
		},
		{
			"_id": "AmmoMag2Vest823218",
			"_tpl": "59e77a2386f7742ee578960a",
			"parentId": "mag2Vest483488",
			"slotId": "cartridges",
			"upd": {
				"StackObjectsCount": 10
			}
		},
		{
			"_id": "mag2Vest281620",
			"_tpl": "559ba5b34bdc2d1f1a8b4582",
			"parentId": "B51642398278805178vaIyRc",
			"slotId": "4",
			"location": {
				"x": 0,
				"y": 1,
				"r": "Horizontal"
			}
		},
		{
			"_id": "AmmoMag2Vest103297",
			"_tpl": "560d61e84bdc2da74d8b4571",
			"parentId": "mag2Vest281620",
			"slotId": "cartridges",
			"upd": {
				"StackObjectsCount": 10
			}
		},
		{
			"_id": "mag3Vest668956",
			"_tpl": "559ba5b34bdc2d1f1a8b4582",
			"parentId": "B51642398278805178vaIyRc",
			"slotId": "6",
			"location": {
				"x": 0,
				"y": 0,
				"r": "Horizontal"
			}
		},
		{
			"_id": "AmmoMag3Vest279924",
			"_tpl": "59e77a2386f7742ee578960a",
			"parentId": "mag3Vest668956",
			"slotId": "cartridges",
			"upd": {
				"StackObjectsCount": 10
			}
		},
		{
			"_id": "mag4Vest89881",
			"_tpl": "559ba5b34bdc2d1f1a8b4582",
			"parentId": "B51642398278805178vaIyRc",
			"slotId": "8",
			"location": {
				"x": 0,
				"y": 0,
				"r": "Horizontal"
			}
		},
		{
			"_id": "AmmoMag4Vest79801",
			"_tpl": "5e023d48186a883be655e551",
			"parentId": "mag4Vest89881",
			"slotId": "cartridges",
			"upd": {
				"StackObjectsCount": 10
			}
		},
		{
			"_id": "mag4Vest505388",
			"_tpl": "559ba5b34bdc2d1f1a8b4582",
			"parentId": "B51642398278805178vaIyRc",
			"slotId": "8",
			"location": {
				"x": 0,
				"y": 1,
				"r": "Horizontal"
			}
		},
		{
			"_id": "AmmoMag4Vest709767",
			"_tpl": "5e023d34e8a400319a28ed44",
			"parentId": "mag4Vest505388",
			"slotId": "cartridges",
			"upd": {
				"StackObjectsCount": 10
			}
		},
		{
			"_id": "magP0Vest4676",
			"_tpl": "5a7ad2e851dfba0016153692",
			"parentId": "B51642398278805178vaIyRc",
			"slotId": "2",
			"location": {
				"x": 0,
				"y": 0,
				"r": "Horizontal"
			}
		},
		{
			"_id": "AmmoMagPVest688315",
			"_tpl": "58864a4f2459770fcc257101",
			"parentId": "magP0Vest4676",
			"slotId": "cartridges",
			"upd": {
				"StackObjectsCount": 33
			}
		},
		{
			"_id": "magP1Vest87819",
			"_tpl": "5a7ad2e851dfba0016153692",
			"parentId": "B51642398278805178vaIyRc",
			"slotId": "5",
			"location": {
				"x": 0,
				"y": 0,
				"r": "Horizontal"
			}
		},
		{
			"_id": "AmmoMagPVest198587",
			"_tpl": "5a3c16fe86f77452b62de32a",
			"parentId": "magP1Vest87819",
			"slotId": "cartridges",
			"upd": {
				"StackObjectsCount": 33
			}
		},
		{
			"_id": "B51642393385561206dGRYCc",
			"_tpl": "5c0116620db834001808a647",
			"parentId": "5c6687d65e9d882c8841f0fd",
			"slotId": "Scabbard"
		},
		{
			"_id": "B51642393943847452MWgosK",
			"_tpl": "5a43943586f77416ad2f06e2",
			"parentId": "5c6687d65e9d882c8841f0fd",
			"slotId": "Headwear"
		},
		{
			"_id": "B51642398938331117pJ6Ufe",
			"_tpl": "572b7f1624597762ae139822",
			"parentId": "5c6687d65e9d882c8841f0fd",
			"slotId": "FaceCover"
		},
		{
			"_id": "B51642396515494308zCncHQ",
			"_tpl": "544a5cde4bdc2d39388b456b",
			"parentId": "5c6687d65e9d882c8841f0fd",
			"slotId": "Backpack"
		},
		{
			"_id": "BP51642398836370268uHZVN",
			"_tpl": "5649b1c04bdc2d16268b457c",
			"parentId": "B51642396515494308zCncHQ",
			"slotId": "main",
			"location": {
				"x": 0,
				"y": 0,
				"r": "Horizontal"
			}
		},
		{
			"_id": "BP516423933489783295y17p",
			"_tpl": "57347d90245977448f7b7f65",
			"parentId": "B51642396515494308zCncHQ",
			"slotId": "main",
			"location": {
				"x": 0,
				"y": 1,
				"r": "Horizontal"
			}
		},
		{
			"_id": "BP51642393845521582pwZnh",
			"_tpl": "57d14e1724597714010c3f4b",
			"parentId": "B51642396515494308zCncHQ",
			"slotId": "main",
			"location": {
				"x": 0,
				"y": 3,
				"r": "Horizontal"
			}
		},
		{
			"_id": "BP51642392066663106x1KLq",
			"_tpl": "55d481904bdc2d8c2f8b456a",
			"parentId": "B51642396515494308zCncHQ",
			"slotId": "main",
			"location": {
				"x": 1,
				"y": 1,
				"r": "Horizontal"
			}
		},
		{
			"_id": "BP51642392227209204ezwpj",
			"_tpl": "5649b1c04bdc2d16268b457c",
			"parentId": "B51642396515494308zCncHQ",
			"slotId": "main",
			"location": {
				"x": 2,
				"y": 0,
				"r": "Horizontal"
			}
		},
		{
			"_id": "BP51642397145762548MI1oR",
			"_tpl": "59e5d83b86f7745aed03d262",
			"parentId": "B51642396515494308zCncHQ",
			"slotId": "main",
			"location": {
				"x": 2,
				"y": 1,
				"r": "Horizontal"
			}
		},
		{
			"_id": "BP51642393881886067b6RNq",
			"_tpl": "5d1b304286f774253763a528",
			"parentId": "B51642396515494308zCncHQ",
			"slotId": "main",
			"location": {
				"x": 2,
				"y": 2,
				"r": "Horizontal"
			}
		},
		{
			"_id": "B51642398845319622ASQqe7",
			"_tpl": "5b44cf1486f77431723e3d05",
			"parentId": "5c6687d65e9d882c8841f0fd",
			"slotId": "ArmorVest",
			"upd": {
				"Repairable": {
					"MaxDurability": 75,
					"Durability": 57
				}
			}
		},
		{
			"_id": "Pocket_478339",
			"_tpl": "57c55f112459772d28133310",
			"parentId": "5c6687d65e9d882c8841f121",
			"slotId": "pocket1",
			"location": {
				"x": 0,
				"y": 0,
				"r": "Horizontal"
			},
			"upd": {
				"SpawnedInSession": true
			}
		}
	],
	"equipment": "5c6687d65e9d882c8841f0fd",
	"stash": "5c6687d65e9d882c8841f0fc",
	"questRaidItems": "5c6687d65e9d882c8841f0fe",
	"questStashItems": "5c6687d65e9d882c8841f0ff",
	"fastPanel": {}
}