{
	"items": [
		{
			"_id": "5c6687d65e9d882c8841f0fd",
			"_tpl": "55d7217a4bdc2d86028b456d"
		},
		{
			"_id": "5c6687d65e9d882c8841f121",
			"_tpl": "557ffd194bdc2d28148b457f",
			"parentId": "5c6687d65e9d882c8841f0fd",
			"slotId": "Pockets"
		},
		{
			"_id": "5c6687d65e9d882c8841f0fc",
			"_tpl": "566abbc34bdc2d92178b4576"
		},
		{
			"_id": "5c6687d65e9d882c8841f0ff",
			"_tpl": "5963866b86f7747bfa1c4462"
		},
		{
			"_id": "5c6687d65e9d882c8841f0fe",
			"_tpl": "5963866286f7747bf429b572"
		},
		{
			"_id": "B51647209081297349pVOHpK",
			"_tpl": "5c0e9f2c86f77432297fe0a3",
			"parentId": "5c6687d65e9d882c8841f0fd",
			"slotId": "TacticalVest"
		},
		{
			"_id": "I2100831885996599QQYhjJu",
			"_tpl": "59d6088586f774275f37482f",
			"parentId": "5c6687d65e9d882c8841f0fd",
			"slotId": "FirstPrimaryWeapon"
		},
		{
			"_id": "I2100839244070902GXKgrQB",
			"_tpl": "59d64ec286f774171d1e0a42",
			"parentId": "I2100831885996599QQYhjJu",
			"slotId": "mod_gas_block"
		},
		{
			"_id": "I2100833337038757GMryd1i",
			"_tpl": "59d64fc686f774171b243fe2",
			"parentId": "I2100831885996599QQYhjJu",
			"slotId": "mod_muzzle"
		},
		{
			"_id": "I2100839525132751ViQ5vw9",
			"_tpl": "59e62cc886f77440d40b52a1",
			"parentId": "I2100831885996599QQYhjJu",
			"slotId": "mod_pistol_grip"
		},
		{
			"_id": "I21008346648999282Ri1F3U",
			"_tpl": "59d6507c86f7741b846413a2",
			"parentId": "I2100831885996599QQYhjJu",
			"slotId": "mod_reciever"
		},
		{
			"_id": "I21008355203657065mkiXII",
			"_tpl": "59d650cf86f7741b846413a4",
			"parentId": "I2100831885996599QQYhjJu",
			"slotId": "mod_sight_rear",
			"upd": {
				"Sight": {
					"SelectedSightMode": 0
				}
			}
		},
		{
			"_id": "I2100834618895836883brrJ",
			"_tpl": "59d6514b86f774171a068a08",
			"parentId": "I2100831885996599QQYhjJu",
			"slotId": "mod_stock"
		},
		{
			"_id": "MagazineWeaponScav2186",
			"_tpl": "5cfe8010d7ad1a59283b14c6",
			"parentId": "I2100831885996599QQYhjJu",
			"slotId": "mod_magazine"
		},
		{
			"_id": "AmmoMag12315",
			"_tpl": "59e0d99486f7744a32234762",
			"parentId": "MagazineWeaponScav2186",
			"slotId": "cartridges",
			"upd": {
				"StackObjectsCount": 50
			}
		},
		{
			"_id": "I21008313563024407sFthFB",
			"_tpl": "59d64f2f86f77417193ef8b3",
			"parentId": "I2100839244070902GXKgrQB",
			"slotId": "mod_handguard"
		},
		{
			"_id": "FuckYouUnlimitedAmmo777590",
			"_tpl": "5857a8bc2459772bad15db29",
			"parentId": "5c6687d65e9d882c8841f0fd",
			"slotId": "SecuredContainer"
		},
		{
			"_id": "iHateThatShit997327",
			"_tpl": "59e4d3d286f774176a36250a",
			"parentId": "FuckYouUnlimitedAmmo777590",
			"slotId": "main",
			"upd": {
				"StackObjectsCount": 60
			}
		},
		{
			"_id": "iHateThatShit268200",
			"_tpl": "59e0d99486f7744a32234762",
			"parentId": "FuckYouUnlimitedAmmo777590",
			"slotId": "main",
			"upd": {
				"StackObjectsCount": 60
			}
		},
		{
			"_id": "iHateThatShit864102",
			"_tpl": "59e4d3d286f774176a36250a",
			"parentId": "FuckYouUnlimitedAmmo777590",
			"slotId": "main",
			"upd": {
				"StackObjectsCount": 60
			}
		},
		{
			"_id": "iHateThatShit927743",
			"_tpl": "5656d7c34bdc2d9d198b4587",
			"parentId": "FuckYouUnlimitedAmmo777590",
			"slotId": "main",
			"upd": {
				"StackObjectsCount": 60
			}
		},
		{
			"_id": "iHateThatShit107838",
			"_tpl": "59e4d3d286f774176a36250a",
			"parentId": "FuckYouUnlimitedAmmo777590",
			"slotId": "main",
			"upd": {
				"StackObjectsCount": 60
			}
		},
		{
			"_id": "iHateThatShit180195",
			"_tpl": "59e4d24686f7741776641ac7",
			"parentId": "FuckYouUnlimitedAmmo777590",
			"slotId": "main",
			"upd": {
				"StackObjectsCount": 60
			}
		},
		{
			"_id": "iHateThatShit511362",
			"_tpl": "59e4d3d286f774176a36250a",
			"parentId": "FuckYouUnlimitedAmmo777590",
			"slotId": "main",
			"upd": {
				"StackObjectsCount": 60
			}
		},
		{
			"_id": "iHateThatShit21968",
			"_tpl": "59e4cf5286f7741778269d8a",
			"parentId": "FuckYouUnlimitedAmmo777590",
			"slotId": "main",
			"upd": {
				"StackObjectsCount": 60
			}
		},
		{
			"_id": "iHateThatShit924180",
			"_tpl": "59e0d99486f7744a32234762",
			"parentId": "FuckYouUnlimitedAmmo777590",
			"slotId": "main",
			"upd": {
				"StackObjectsCount": 60
			}
		},
		{
			"_id": "mag1Vest32186",
			"_tpl": "59fafc9386f774067d462453",
			"parentId": "B51647209081297349pVOHpK",
			"slotId": "2",
			"location": {
				"x": 0,
				"y": 0,
				"r": "Horizontal"
			}
		},
		{
			"_id": "AmmoMag1Vest972485",
			"_tpl": "59e0d99486f7744a32234762",
			"parentId": "mag1Vest32186",
			"slotId": "cartridges",
			"upd": {
				"StackObjectsCount": 30
			}
		},
		{
			"_id": "mag2Vest963688",
			"_tpl": "59fafc9386f774067d462453",
			"parentId": "B51647209081297349pVOHpK",
			"slotId": "4",
			"location": {
				"x": 0,
				"y": 0,
				"r": "Horizontal"
			}
		},
		{
			"_id": "AmmoMag2Vest595569",
			"_tpl": "59e4d3d286f774176a36250a",
			"parentId": "mag2Vest963688",
			"slotId": "cartridges",
			"upd": {
				"StackObjectsCount": 30
			}
		},
		{
			"_id": "mag4Vest31184",
			"_tpl": "59fafc9386f774067d462453",
			"parentId": "B51647209081297349pVOHpK",
			"slotId": "7",
			"location": {
				"x": 0,
				"y": 0,
				"r": "Horizontal"
			}
		},
		{
			"_id": "AmmoMag4Vest621800",
			"_tpl": "59e4d3d286f774176a36250a",
			"parentId": "mag4Vest31184",
			"slotId": "cartridges",
			"upd": {
				"StackObjectsCount": 30
			}
		},
		{
			"_id": "B51647205651993635wkbvlT",
			"_tpl": "57e26fc7245977162a14b800",
			"parentId": "5c6687d65e9d882c8841f0fd",
			"slotId": "Scabbard"
		},
		{
			"_id": "B51647202982473483pYND7c",
			"_tpl": "5d6d2e22a4b9361bd5780d05",
			"parentId": "5c6687d65e9d882c8841f0fd",
			"slotId": "Eyewear"
		},
		{
			"_id": "B51647207877995113JhTiGA",
			"_tpl": "5bd06f5d86f77427101ad47c",
			"parentId": "5c6687d65e9d882c8841f0fd",
			"slotId": "FaceCover"
		},
		{
			"_id": "B516472087619530073deg5D",
			"_tpl": "56e33634d2720bd8058b456b",
			"parentId": "5c6687d65e9d882c8841f0fd",
			"slotId": "Backpack"
		},
		{
			"_id": "BP51647206876133981LqENY",
			"_tpl": "57347c93245977448d35f6e3",
			"parentId": "B516472087619530073deg5D",
			"slotId": "main",
			"location": {
				"x": 0,
				"y": 0,
				"r": "Horizontal"
			}
		},
		{
			"_id": "BP51647209144879532q6O9T",
			"_tpl": "590c5d4b86f774784e1b9c45",
			"parentId": "B516472087619530073deg5D",
			"slotId": "main",
			"location": {
				"x": 0,
				"y": 1,
				"r": "Horizontal"
			}
		},
		{
			"_id": "BP51647207342518439JpLiZ",
			"_tpl": "577e1c9d2459773cd707c525",
			"parentId": "B516472087619530073deg5D",
			"slotId": "main",
			"location": {
				"x": 1,
				"y": 0,
				"r": "Horizontal"
			}
		},
		{
			"_id": "BP51647201547890198QfHfV",
			"_tpl": "57347d9c245977448b40fa85",
			"parentId": "B516472087619530073deg5D",
			"slotId": "main",
			"location": {
				"x": 1,
				"y": 1,
				"r": "Horizontal"
			}
		},
		{
			"_id": "Pocket_613747",
			"_tpl": "59e3577886f774176a362503",
			"parentId": "5c6687d65e9d882c8841f121",
			"slotId": "pocket1",
			"location": {
				"x": 0,
				"y": 0,
				"r": "Horizontal"
			},
			"upd": {
				"SpawnedInSession": true
			}
		}
	],
	"equipment": "5c6687d65e9d882c8841f0fd",
	"stash": "5c6687d65e9d882c8841f0fc",
	"questRaidItems": "5c6687d65e9d882c8841f0fe",
	"questStashItems": "5c6687d65e9d882c8841f0ff",
	"fastPanel": {}
}