{
	"items": [
		{
			"_id": "5c6687d65e9d882c8841f0fd",
			"_tpl": "55d7217a4bdc2d86028b456d"
		},
		{
			"_id": "5c6687d65e9d882c8841f121",
			"_tpl": "557ffd194bdc2d28148b457f",
			"parentId": "5c6687d65e9d882c8841f0fd",
			"slotId": "Pockets"
		},
		{
			"_id": "5c6687d65e9d882c8841f0fc",
			"_tpl": "566abbc34bdc2d92178b4576"
		},
		{
			"_id": "5c6687d65e9d882c8841f0ff",
			"_tpl": "5963866b86f7747bfa1c4462"
		},
		{
			"_id": "5c6687d65e9d882c8841f0fe",
			"_tpl": "5963866286f7747bf429b572"
		},
		{
			"_id": "B51647161100483072OSlSXB",
			"_tpl": "5d5d646386f7742797261fd9",
			"parentId": "5c6687d65e9d882c8841f0fd",
			"slotId": "TacticalVest"
		},
		{
			"_id": "I33102303730031505TZLMDy",
			"_tpl": "583990e32459771419544dd2",
			"parentId": "5c6687d65e9d882c8841f0fd",
			"slotId": "FirstPrimaryWeapon"
		},
		{
			"_id": "I33102307989103931N2Kw00",
			"_tpl": "5649ad3f4bdc2df8348b4585",
			"parentId": "I33102303730031505TZLMDy",
			"slotId": "mod_pistol_grip"
		},
		{
			"_id": "MagazineWeaponScav798",
			"_tpl": "5cbdaf89ae9215000e5b9c94",
			"parentId": "I33102303730031505TZLMDy",
			"slotId": "mod_magazine"
		},
		{
			"_id": "AmmoMag1704",
			"_tpl": "56dff421d2720b5f5a8b4567",
			"parentId": "MagazineWeaponScav798",
			"slotId": "cartridges",
			"upd": {
				"StackObjectsCount": 30
			}
		},
		{
			"_id": "I33102308164590742qZRmUg",
			"_tpl": "57dc324a24597759501edc20",
			"parentId": "I33102303730031505TZLMDy",
			"slotId": "mod_muzzle"
		},
		{
			"_id": "I33102309203048350rvJr4i",
			"_tpl": "59d36a0086f7747e673f3946",
			"parentId": "I33102303730031505TZLMDy",
			"slotId": "mod_gas_block"
		},
		{
			"_id": "I33102302388811623UyrSOM",
			"_tpl": "56dfef82d2720bbd668b4567",
			"parentId": "I33102303015895963IGu8iz",
			"slotId": "cartridges",
			"location": 0,
			"upd": {
				"StackObjectsCount": 30
			}
		},
		{
			"_id": "I33102301697240347uAkuT7",
			"_tpl": "57dc32dc245977596d4ef3d3",
			"parentId": "I33102309203048350rvJr4i",
			"slotId": "mod_handguard"
		},
		{
			"_id": "FuckYouUnlimitedAmmo162247",
			"_tpl": "5857a8bc2459772bad15db29",
			"parentId": "5c6687d65e9d882c8841f0fd",
			"slotId": "SecuredContainer"
		},
		{
			"_id": "iHateThatShit739747",
			"_tpl": "56dfef82d2720bbd668b4567",
			"parentId": "FuckYouUnlimitedAmmo162247",
			"slotId": "main",
			"upd": {
				"StackObjectsCount": 60
			}
		},
		{
			"_id": "iHateThatShit718228",
			"_tpl": "56dff338d2720bbd668b4569",
			"parentId": "FuckYouUnlimitedAmmo162247",
			"slotId": "main",
			"upd": {
				"StackObjectsCount": 60
			}
		},
		{
			"_id": "iHateThatShit539697",
			"_tpl": "56dff3afd2720bba668b4567",
			"parentId": "FuckYouUnlimitedAmmo162247",
			"slotId": "main",
			"upd": {
				"StackObjectsCount": 60
			}
		},
		{
			"_id": "iHateThatShit52188",
			"_tpl": "56dff338d2720bbd668b4569",
			"parentId": "FuckYouUnlimitedAmmo162247",
			"slotId": "main",
			"upd": {
				"StackObjectsCount": 60
			}
		},
		{
			"_id": "iHateThatShit722555",
			"_tpl": "56dff2ced2720bb4668b4567",
			"parentId": "FuckYouUnlimitedAmmo162247",
			"slotId": "main",
			"upd": {
				"StackObjectsCount": 60
			}
		},
		{
			"_id": "iHateThatShit401138",
			"_tpl": "56dff2ced2720bb4668b4567",
			"parentId": "FuckYouUnlimitedAmmo162247",
			"slotId": "main",
			"upd": {
				"StackObjectsCount": 60
			}
		},
		{
			"_id": "iHateThatShit478950",
			"_tpl": "56dff3afd2720bba668b4567",
			"parentId": "FuckYouUnlimitedAmmo162247",
			"slotId": "main",
			"upd": {
				"StackObjectsCount": 60
			}
		},
		{
			"_id": "iHateThatShit871983",
			"_tpl": "56dff0bed2720bb0668b4567",
			"parentId": "FuckYouUnlimitedAmmo162247",
			"slotId": "main",
			"upd": {
				"StackObjectsCount": 60
			}
		},
		{
			"_id": "iHateThatShit443204",
			"_tpl": "56dfef82d2720bbd668b4567",
			"parentId": "FuckYouUnlimitedAmmo162247",
			"slotId": "main",
			"upd": {
				"StackObjectsCount": 60
			}
		},
		{
			"_id": "mag0Vest78606",
			"_tpl": "5aaa4194e5b5b055d06310a5",
			"parentId": "B51647161100483072OSlSXB",
			"slotId": "3",
			"location": {
				"x": 0,
				"y": 0,
				"r": "Horizontal"
			}
		},
		{
			"_id": "AmmoMag0Vest701274",
			"_tpl": "56dff0bed2720bb0668b4567",
			"parentId": "mag0Vest78606",
			"slotId": "cartridges",
			"upd": {
				"StackObjectsCount": 30
			}
		},
		{
			"_id": "mag1Vest336867",
			"_tpl": "5aaa4194e5b5b055d06310a5",
			"parentId": "B51647161100483072OSlSXB",
			"slotId": "5",
			"location": {
				"x": 0,
				"y": 0,
				"r": "Horizontal"
			}
		},
		{
			"_id": "AmmoMag1Vest512274",
			"_tpl": "56dfef82d2720bbd668b4567",
			"parentId": "mag1Vest336867",
			"slotId": "cartridges",
			"upd": {
				"StackObjectsCount": 30
			}
		},
		{
			"_id": "StackAmmo23600150253",
			"_tpl": "56dff216d2720bbd668b4568",
			"parentId": "B51647161100483072OSlSXB",
			"slotId": "1",
			"upd": {
				"StackObjectsCount": 10
			}
		},
		{
			"_id": "StackAmmo33475475943",
			"_tpl": "56dff4a2d2720bbd668b456a",
			"parentId": "B51647161100483072OSlSXB",
			"slotId": "7",
			"upd": {
				"StackObjectsCount": 30
			}
		},
		{
			"_id": "B51647165408446182Aaw5b7",
			"_tpl": "5bffdc370db834001d23eca8",
			"parentId": "5c6687d65e9d882c8841f0fd",
			"slotId": "Scabbard"
		},
		{
			"_id": "B5164716600942386782g8t5",
			"_tpl": "5aa2b8d7e5b5b00014028f4a",
			"parentId": "5c6687d65e9d882c8841f0fd",
			"slotId": "Headwear"
		},
		{
			"_id": "B51647166852683878hYE5C9",
			"_tpl": "5c0d32fcd174af02a1659c75",
			"parentId": "5c6687d65e9d882c8841f0fd",
			"slotId": "Eyewear"
		},
		{
			"_id": "B51647162549277570G0lkrB",
			"_tpl": "56e33634d2720bd8058b456b",
			"parentId": "5c6687d65e9d882c8841f0fd",
			"slotId": "Backpack"
		},
		{
			"_id": "BP51647162291505149DTXcU",
			"_tpl": "5780cf722459777a5108b9a1",
			"parentId": "B51647162549277570G0lkrB",
			"slotId": "main",
			"location": {
				"x": 0,
				"y": 0,
				"r": "Horizontal"
			}
		},
		{
			"_id": "BP51647162046041588rr8hS",
			"_tpl": "5780cfa52459777dfb276eb1",
			"parentId": "B51647162549277570G0lkrB",
			"slotId": "main",
			"location": {
				"x": 0,
				"y": 1,
				"r": "Horizontal"
			}
		},
		{
			"_id": "BP51647163686288803FwMgR",
			"_tpl": "5e2af29386f7746d4159f077",
			"parentId": "B51647162549277570G0lkrB",
			"slotId": "main",
			"location": {
				"x": 0,
				"y": 2,
				"r": "Horizontal"
			}
		},
		{
			"_id": "BP51647161850042849gQ01U",
			"_tpl": "590a3b0486f7743954552bdb",
			"parentId": "B51647162549277570G0lkrB",
			"slotId": "main",
			"location": {
				"x": 1,
				"y": 0,
				"r": "Horizontal"
			}
		},
		{
			"_id": "BP51647164129870394FsJlO",
			"_tpl": "57347c5b245977448d35f6e1",
			"parentId": "B51647162549277570G0lkrB",
			"slotId": "main",
			"location": {
				"x": 1,
				"y": 1,
				"r": "Horizontal"
			}
		},
		{
			"_id": "B516471633978595810ymnH5",
			"_tpl": "5b44d22286f774172b0c9de8",
			"parentId": "5c6687d65e9d882c8841f0fd",
			"slotId": "ArmorVest",
			"upd": {
				"Repairable": {
					"MaxDurability": 70,
					"Durability": 26
				}
			}
		},
		{
			"_id": "Pocket_157463",
			"_tpl": "590c2c9c86f774245b1f03f2",
			"parentId": "5c6687d65e9d882c8841f121",
			"slotId": "pocket1",
			"location": {
				"x": 0,
				"y": 0,
				"r": "Horizontal"
			},
			"upd": {
				"SpawnedInSession": true
			}
		},
		{
			"_id": "Pocket_249647",
			"_tpl": "5c1d0dc586f7744baf2e7b79",
			"parentId": "5c6687d65e9d882c8841f121",
			"slotId": "pocket2",
			"location": {
				"x": 0,
				"y": 0,
				"r": "Horizontal"
			},
			"upd": {
				"SpawnedInSession": true
			}
		},
		{
			"_id": "Pocket_800700",
			"_tpl": "59e3606886f77417674759a5",
			"parentId": "5c6687d65e9d882c8841f121",
			"slotId": "pocket3",
			"location": {
				"x": 0,
				"y": 0,
				"r": "Horizontal"
			},
			"upd": {
				"SpawnedInSession": true
			}
		}
	],
	"equipment": "5c6687d65e9d882c8841f0fd",
	"stash": "5c6687d65e9d882c8841f0fc",
	"questRaidItems": "5c6687d65e9d882c8841f0fe",
	"questStashItems": "5c6687d65e9d882c8841f0ff",
	"fastPanel": {}
}